rm_runner/__init__.py
rm_runner/cli.py
rm_runner/ec2_runner.py
rm_runner/utils.py
rm_runner-0.1.0.dist-info/METADATA
rm_runner-0.1.0.dist-info/WHEEL
rm_runner-0.1.0.dist-info/top_level.txt
rm_runner-0.1.0.dist-info/RECORD
